odoo/addons/sale_order_line_remove/README.rst
odoo/addons/sale_order_line_remove/__init__.py
odoo/addons/sale_order_line_remove/__manifest__.py
odoo/addons/sale_order_line_remove/i18n/sale_order_line_remove.pot
odoo/addons/sale_order_line_remove/models/__init__.py
odoo/addons/sale_order_line_remove/models/sale_order.py
odoo/addons/sale_order_line_remove/readme/CONTRIBUTORS.rst
odoo/addons/sale_order_line_remove/readme/DESCRIPTION.rst
odoo/addons/sale_order_line_remove/readme/USAGE.rst
odoo/addons/sale_order_line_remove/static/description/icon.png
odoo/addons/sale_order_line_remove/static/description/index.html
odoo/addons/sale_order_line_remove/tests/__init__.py
odoo/addons/sale_order_line_remove/tests/test_sale_order_line.py
odoo13_addon_sale_order_line_remove-13.0.1.0.1.dev3.dist-info/METADATA
odoo13_addon_sale_order_line_remove-13.0.1.0.1.dev3.dist-info/WHEEL
odoo13_addon_sale_order_line_remove-13.0.1.0.1.dev3.dist-info/top_level.txt
odoo13_addon_sale_order_line_remove-13.0.1.0.1.dev3.dist-info/RECORD
